flask_restx_patched
