Metadata-Version: 1.1
Name: flask-restx-patched
Version: 0.1.16
Summary: Forked from flask-restplus-patched. Extends flask-restx so it can handle Marshmallow schemas and Webargs arguments.
Home-page: https://github.com/justinrubek/flask-restx-patched
Author: Justin Rubek
Author-email: justin@levitytech.net
License: UNKNOWN
Platform: any
Classifier: Development Status :: 2 - Pre-Alpha
Classifier: Environment :: Web Environment
Classifier: Intended Audience :: Developers
Classifier: Operating System :: OS Independent
Classifier: Programming Language :: Python
Classifier: Programming Language :: Python :: 3.8
